corazaytubos_sim/__init__.py
corazaytubos_sim/fluidos.py
corazaytubos_sim-0.0.1.dist-info/METADATA
corazaytubos_sim-0.0.1.dist-info/WHEEL
corazaytubos_sim-0.0.1.dist-info/top_level.txt
corazaytubos_sim-0.0.1.dist-info/RECORD
